{"cameraMode":{"drawMode":0,"name":"Shaded","section":"Shading Mode"},"sceneLighting":true,"audioPlay":false,"sceneViewState":{"m_AlwaysRefresh":false,"showFog":true,"showSkybox":true,"showFlares":true,"showImageEffects":true,"showParticleSystems":true,"showVisualEffectGraphs":true,"m_FxEnabled":true},"in2DMode":false,"pivot":{"x":-13.90219497680664,"y":0.20875784754753114,"z":-8.117717742919922},"rotation":{"x":0.12280291318893433,"y":0.5975634455680847,"z":-0.0932483971118927,"w":0.7868765592575073},"size":10.550885200500489,"orthographic":false}